{
  "4": {
    "ID": 4,
    "TID": 0,
    "Code": 1001,
    "Name": "横剑击",
    "Description": "剑士的基础招式，无消耗",
    "Level": 1,
    "MaxLevel": 3,
    "Type": "普通攻击",
    "Icon": "Prefabs/UI/Icon/skill_icon_000",
    "TargetType": "单位",
    "CD": 1.5,
    "SpellRange": 3500,
    "IntonateTime": 0,
    "Cost": 0,
    "AnimName": "Attack",
    "ReqLevel": 0,
    "IsMissile": 0,
    "Missile": "",
    "MissileSpeed": 0,
    "HitArt": "Effects/Hits/Holy hit",
    "Area": 0,
    "HitDelay": "[0.5]",
    "BUFF": "",
    "AD": 0,
    "AP": 0,
    "ADC": 1,
    "APC": 0
  },
  "5": {
    "ID": 5,
    "TID": 0,
    "Code": 1001,
    "Name": "横剑击",
    "Description": "剑士的基础招式，无消耗",
    "Level": 2,
    "MaxLevel": 3,
    "Type": "普通攻击",
    "Icon": "Prefabs/UI/Icon/skill_icon_000",
    "TargetType": "单位",
    "CD": 1.5,
    "SpellRange": 3500,
    "IntonateTime": 0,
    "Cost": 0,
    "AnimName": "Attack",
    "ReqLevel": 0,
    "IsMissile": 0,
    "Missile": "",
    "MissileSpeed": 0,
    "HitArt": "",
    "Area": 0,
    "HitDelay": "[0.5]",
    "BUFF": "",
    "AD": 30,
    "AP": 0,
    "ADC": 1,
    "APC": 0
  },
  "6": {
    "ID": 6,
    "TID": 0,
    "Code": 1001,
    "Name": "横剑击",
    "Description": "剑士的基础招式，无消耗",
    "Level": 3,
    "MaxLevel": 3,
    "Type": "普通攻击",
    "Icon": "Prefabs/UI/Icon/skill_icon_000",
    "TargetType": "单位",
    "CD": 1.5,
    "SpellRange": 3500,
    "IntonateTime": 0,
    "Cost": 0,
    "AnimName": "Attack",
    "ReqLevel": 0,
    "IsMissile": 0,
    "Missile": "",
    "MissileSpeed": 0,
    "HitArt": "",
    "Area": 0,
    "HitDelay": "[0.5]",
    "BUFF": "",
    "AD": 60,
    "AP": 0,
    "ADC": 1,
    "APC": 0
  },
  "7": {
    "ID": 7,
    "TID": 0,
    "Code": 1002,
    "Name": "剑刃弑心",
    "Description": "对单个目标照成物理攻击，添加流血效果",
    "Level": 1,
    "MaxLevel": 1,
    "Type": "技能",
    "Icon": "Prefabs/UI/Icon/skill_icon_000",
    "TargetType": "单位",
    "CD": 5,
    "SpellRange": 3500,
    "IntonateTime": 0,
    "Cost": 20,
    "AnimName": "SpellA",
    "ReqLevel": 5,
    "IsMissile": 0,
    "Missile": "",
    "MissileSpeed": 0,
    "HitArt": "",
    "Area": 0,
    "HitDelay": "[0.5]",
    "BUFF": "",
    "AD": 150,
    "AP": 0,
    "ADC": 1,
    "APC": 0
  },
  "8": {
    "ID": 8,
    "TID": 0,
    "Code": 1002,
    "Name": "剑荡八荒",
    "Description": "对自身周围造成范围伤害",
    "Level": 1,
    "MaxLevel": 1,
    "Type": "技能",
    "Icon": "Prefabs/UI/Icon/skill_icon_000",
    "TargetType": "None",
    "CD": 3.5,
    "SpellRange": 0,
    "IntonateTime": 0,
    "Cost": 25,
    "AnimName": "SpellB",
    "ReqLevel": 10,
    "IsMissile": 0,
    "Missile": "",
    "MissileSpeed": 0,
    "HitArt": "",
    "Area": 4000,
    "HitDelay": "[0.3,0.6,0.9]",
    "BUFF": "[1]",
    "AD": 100,
    "AP": 0,
    "ADC": 0.8,
    "APC": 0
  },
  "9": {
    "ID": 9,
    "TID": 1,
    "Code": 2001,
    "Name": "木棍戳戳",
    "Description": "法师的基础法术，无消耗",
    "Level": 1,
    "MaxLevel": 1,
    "Type": "普通攻击",
    "Icon": "Prefabs/UI/Icon/skill_icon_001_2001",
    "TargetType": "单位",
    "CD": 1.5,
    "SpellRange": 3500,
    "IntonateTime": 0.9,
    "Cost": 0,
    "AnimName": "Attack",
    "ReqLevel": 0,
    "IsMissile": 0,
    "Missile": "",
    "MissileSpeed": 0,
    "HitArt": "",
    "Area": 0,
    "HitDelay": "[0]",
    "BUFF": "",
    "AD": 0,
    "AP": 200,
    "ADC": 1.2,
    "APC": 1
  },
  "10": {
    "ID": 10,
    "TID": 1,
    "Code": 2002,
    "Name": "火球术",
    "Description": "对单体目标造成法术伤害",
    "Level": 1,
    "MaxLevel": 1,
    "Type": "技能",
    "Icon": "Prefabs/UI/Icon/skill_icon_001_2002",
    "TargetType": "单位",
    "CD": 5,
    "SpellRange": 30000,
    "IntonateTime": 1.5,
    "Cost": 35,
    "AnimName": "Intonate",
    "ReqLevel": 5,
    "IsMissile": 1,
    "Missile": "Effects/Fly/FireBall",
    "MissileSpeed": 15000,
    "HitArt": "Effects/Hits/Explosion",
    "Area": 4000,
    "HitDelay": "[0.2]",
    "BUFF": "",
    "AD": 0,
    "AP": 250,
    "ADC": 1.5,
    "APC": 1
  }
}